bmrb_starobj-1.0.0.dist-info/licenses/LICENSE
starobj/__init__.py
starobj/_baseclass.py
starobj/db.py
starobj/entry.py
starobj/error.py
starobj/parser.py
starobj/stardict.py
starobj/startable.py
starobj/unparser.py
bmrb_starobj-1.0.0.dist-info/METADATA
bmrb_starobj-1.0.0.dist-info/WHEEL
bmrb_starobj-1.0.0.dist-info/top_level.txt
bmrb_starobj-1.0.0.dist-info/RECORD
