Metadata-Version: 2.4
Name: bmrb-starobj
Version: 1.0.0
Summary: Table-based storage for BMRB's NMR-STAR 3.x
Author-email: BMRB <help@bmrb.io>
License-Expression: MIT
Project-URL: Homepage, https://github.com/bmrb-io/starobj
Project-URL: Repository, https://github.com/bmrb-io/starobj
Keywords: NMR-STAR,BMRB,NMR,spectroscopy,database
Classifier: Development Status :: 5 - Production/Stable
Classifier: Intended Audience :: Science/Research
Classifier: Operating System :: OS Independent
Classifier: Programming Language :: Python :: 3
Classifier: Programming Language :: Python :: 3.8
Classifier: Programming Language :: Python :: 3.9
Classifier: Programming Language :: Python :: 3.10
Classifier: Programming Language :: Python :: 3.11
Classifier: Programming Language :: Python :: 3.12
Classifier: Programming Language :: Python :: 3.13
Classifier: Topic :: Scientific/Engineering :: Bio-Informatics
Requires-Python: >=3.8
License-File: LICENSE
Requires-Dist: bmrb-sas==1.0.0
Requires-Dist: ply<3.12,>=3.11
Requires-Dist: psycopg2>=2.9
Dynamic: license-file
